LICENSE
MANIFEST.in
README.rst
setup.py
djrillcelery/__init__.py
djrillcelery/tasks.py
djrillcelery.egg-info/PKG-INFO
djrillcelery.egg-info/SOURCES.txt
djrillcelery.egg-info/dependency_links.txt
djrillcelery.egg-info/not-zip-safe
djrillcelery.egg-info/requires.txt
djrillcelery.egg-info/top_level.txt
djrillcelery/mail/__init__.py
djrillcelery/mail/backends.py