Metadata-Version: 1.1
Name: djrillcelery
Version: 0.1
Summary: Mandrill transactional email for Django in conjunction with Celery
Home-page: https://github.com/jayfk/DjrillCelery/
Author: Jannis Gebauer <ja.geb@me.com>
Author-email: ja.geb@me.com
License: BSD License
Keywords: django,mailchimp,mandrill,email,email backend,djrill
Platform: UNKNOWN
Classifier: Programming Language :: Python
Classifier: Programming Language :: Python :: Implementation :: PyPy
Classifier: Programming Language :: Python :: Implementation :: CPython
Classifier: Programming Language :: Python :: 2.6
Classifier: Programming Language :: Python :: 2.7
Classifier: Programming Language :: Python :: 3
Classifier: Programming Language :: Python :: 3.2
Classifier: Programming Language :: Python :: 3.3
Classifier: Programming Language :: Python :: 3.4
Classifier: License :: OSI Approved :: BSD License
Classifier: Topic :: Software Development :: Libraries :: Python Modules
Classifier: Framework :: Django
Classifier: Environment :: Web Environment
